{"media_type": "movie", "section_id": "1", "library_name": "Movies", "rating_key": "7036", "parent_rating_key": "", "grandparent_rating_key": "", "title": "THE_DUFF.Title34", "parent_title": "", "grandparent_title": "", "original_title": "", "sort_title": "", "edition_title": "", "media_index": "", "parent_media_index": "", "studio": "Wonderland Sound and Vision", "content_rating": "PG-13", "summary": "Bianca's universe turns upside down when she learns that her high school refers to her as a \u2018DUFF' (Designated Ugly Fat Friend). Hoping to erase that label, she enlists the help of a charming jock and her favorite teacher. Together they'll face the school's mean girl and remind everyone that we are all someone's DUFF\u2026 and that's totally fine.", "tagline": "You either know one, you have one, or you are one.", "rating": "7.3", "rating_image": "rottentomatoes://image.rating.ripe", "audience_rating": "6.6", "audience_rating_image": "rottentomatoes://image.rating.upright", "user_rating": "", "duration": "6074651", "year": "2015", "parent_year": "", "grandparent_year": "", "thumb": "/library/metadata/7036/thumb/1682937150", "parent_thumb": "", "grandparent_thumb": "", "art": "/library/metadata/7036/art/1682937150", "banner": "", "originally_available_at": "2015-02-20", "added_at": "1568256766", "updated_at": "1682937150", "last_viewed_at": "1677970668", "guid": "plex://movie/5d776ae2fb0d55001f554583", "parent_guid": "", "grandparent_guid": "", "directors": ["Ari Sandel"], "writers": ["Josh A. Cagan", "Kody Keplinger", "Kelli Lee"], "actors": ["Mae Whitman", "Robbie Amell", "Bella Thorne", "Skyler Samuels", "Bianca A. Santos", "Romany Malco", "Ken Jeong", "Chris Wylde", "Allison Janney", "Seth Meriwether", "Rebecca Weil", "Brian Dewar McNamara", "Benjamin Davis", "Lai-Ling Bernstein", "Nick Eversman", "Erick Chavarria", "Demetrius Bridges"], "genres": ["Comedy", "Romance"], "labels": [], "collections": [], "guids": ["imdb://tt1666801", "tmdb://272693", "tvdb://2340"], "markers": [{"id": 37714, "type": "credits", "start_time_offset": 5733180, "end_time_offset": 5803180, "first": true, "final": false}, {"id": 37714, "type": "credits", "start_time_offset": 5819180, "end_time_offset": 5841180, "first": false, "final": false}, {"id": 37714, "type": "credits", "start_time_offset": 5861180, "end_time_offset": 6074645, "first": false, "final": true}], "parent_guids": [], "grandparent_guids": [], "full_title": "THE_DUFF.Title34", "children_count": 0, "live": 0, "media_info": [{"id": "15324", "container": "mp4", "bitrate": "1501", "height": "304", "width": "720", "aspect_ratio": "2.35", "video_codec": "h264", "video_resolution": "sd", "video_full_resolution": "SD", "video_framerate": "24p", "video_profile": "main", "audio_codec": "aac", "audio_channels": "6", "audio_channel_layout": "5.1", "audio_profile": "lc", "optimized_version": 0, "channel_call_sign": "", "channel_identifier": "", "channel_thumb": "", "parts": [{"id": "15326", "file": "/movies/The DUFF (2015)/The DUFF (2015) 480p AAC.mp4", "file_size": "1143827772", "indexes": 0, "streams": [{"id": "31509", "type": "1", "video_codec": "h264", "video_codec_level": "30", "video_bitrate": "1047", "video_bit_depth": "8", "video_chroma_subsampling": "4:2:0", "video_color_primaries": "smpte170m", "video_color_range": "tv", "video_color_space": "smpte170m", "video_color_trc": "bt709", "video_dynamic_range": "SDR", "video_frame_rate": "23.976", "video_ref_frames": "1", "video_height": "304", "video_width": "720", "video_language": "", "video_language_code": "", "video_profile": "main", "video_scan_type": "progressive", "selected": 0}, {"id": "31510", "type": "2", "audio_codec": "aac", "audio_bitrate": "448", "audio_bitrate_mode": "", "audio_channels": "6", "audio_channel_layout": "5.1", "audio_sample_rate": "48000", "audio_language": "English", "audio_language_code": "eng", "audio_profile": "lc", "selected": 1}, {"id": "31511", "type": "3", "subtitle_codec": "vobsub", "subtitle_container": "", "subtitle_format": "", "subtitle_forced": 0, "subtitle_location": "embedded", "subtitle_language": "English", "subtitle_language_code": "eng", "selected": 0}, {"id": "31512", "type": "3", "subtitle_codec": "vobsub", "subtitle_container": "", "subtitle_format": "", "subtitle_forced": 0, "subtitle_location": "embedded", "subtitle_language": "English", "subtitle_language_code": "eng", "selected": 0}], "selected": 0}]}], "_cache_time": 1683902278}