{"media_type": "movie", "section_id": "1", "library_name": "Movies", "rating_key": "4732", "parent_rating_key": "", "grandparent_rating_key": "", "title": "MUCH_ADO_ABOUT_NOTHING.Title1", "parent_title": "", "grandparent_title": "", "original_title": "", "sort_title": "", "edition_title": "", "media_index": "", "parent_media_index": "", "studio": "Say It Like You Mean It!", "content_rating": "", "summary": "Adapted for classroom use, the 'Say It Like You Mean It!' Much Ado About Nothing will showcase the Bard's work like never before, setting the classic tale of the four lovers on today's streets of London city.", "tagline": "Thou and I are too wise to woo peacably.", "rating": "", "rating_image": "", "audience_rating": "", "audience_rating_image": "", "user_rating": "", "duration": "6532394", "year": "2020", "parent_year": "", "grandparent_year": "", "thumb": "/library/metadata/4732/thumb/1682672220", "parent_thumb": "", "grandparent_thumb": "", "art": "/library/metadata/4732/art/1682672220", "banner": "", "originally_available_at": "2020-08-22", "added_at": "1569787840", "updated_at": "1682672220", "last_viewed_at": "1686437509", "guid": "plex://movie/5f40bb68fea1a1003fb64717", "parent_guid": "", "grandparent_guid": "", "directors": ["Laura Mary Kruse"], "writers": ["Laura Mary Kruse", "William Shakespeare"], "actors": [], "genres": ["Comedy"], "labels": [], "collections": [], "guids": ["imdb://tt3875562"], "markers": [{"id": 37714, "type": "credits", "start_time_offset": 6303155, "end_time_offset": 6532395, "first": true, "final": true}], "parent_guids": [], "grandparent_guids": [], "full_title": "MUCH_ADO_ABOUT_NOTHING.Title1", "children_count": 0, "live": 0, "media_info": [{"id": "10346", "container": "mp4", "bitrate": "1650", "height": "404", "width": "720", "aspect_ratio": "1.78", "video_codec": "h264", "video_resolution": "sd", "video_full_resolution": "SD", "video_framerate": "24p", "video_profile": "main", "audio_codec": "aac", "audio_channels": "6", "audio_channel_layout": "5.1", "audio_profile": "lc", "optimized_version": 0, "channel_call_sign": "", "channel_identifier": "", "channel_thumb": "", "parts": [{"id": "10347", "file": "/movies/Much Ado About Nothing/Much Ado About Nothing 480p AAC.mp4", "file_size": "1350876589", "indexes": 0, "streams": [{"id": "21277", "type": "1", "video_codec": "h264", "video_codec_level": "30", "video_bitrate": "1198", "video_bit_depth": "8", "video_chroma_subsampling": "4:2:0", "video_color_primaries": "smpte170m", "video_color_range": "tv", "video_color_space": "smpte170m", "video_color_trc": "bt709", "video_dynamic_range": "SDR", "video_frame_rate": "23.976", "video_ref_frames": "1", "video_height": "404", "video_width": "720", "video_language": "", "video_language_code": "", "video_profile": "main", "video_scan_type": "progressive", "selected": 0}, {"id": "21278", "type": "2", "audio_codec": "aac", "audio_bitrate": "448", "audio_bitrate_mode": "", "audio_channels": "6", "audio_channel_layout": "5.1", "audio_sample_rate": "48000", "audio_language": "English", "audio_language_code": "eng", "audio_profile": "lc", "selected": 1}, {"id": "21279", "type": "3", "subtitle_codec": "vobsub", "subtitle_container": "", "subtitle_format": "", "subtitle_forced": 0, "subtitle_location": "embedded", "subtitle_language": "English", "subtitle_language_code": "eng", "selected": 0}], "selected": 0}]}], "_cache_time": 1686438160}