<?xml version="1.0" encoding="UTF-8" ?>
<lfm status="ok"><artist><name>Tom Petty &amp; The Heartbreakers</name>
<mbid>f93dbc64-6f08-4033-bcc7-8a0bb4689849</mbid>
<url>https://www.last.fm/music/+noredirect/Tom+Petty+&amp;+The+Heartbreakers</url>
<image size="small">https://lastfm.freetls.fastly.net/i/u/34s/2a96cbd8b46e442fc41c2b86b821562f.png</image>
<image size="medium">https://lastfm.freetls.fastly.net/i/u/64s/2a96cbd8b46e442fc41c2b86b821562f.png</image>
<image size="large">https://lastfm.freetls.fastly.net/i/u/174s/2a96cbd8b46e442fc41c2b86b821562f.png</image>
<image size="extralarge">https://lastfm.freetls.fastly.net/i/u/300x300/2a96cbd8b46e442fc41c2b86b821562f.png</image>
<image size="mega">https://lastfm.freetls.fastly.net/i/u/300x300/2a96cbd8b46e442fc41c2b86b821562f.png</image>
<image size="">https://lastfm.freetls.fastly.net/i/u/300x300/2a96cbd8b46e442fc41c2b86b821562f.png</image>
<streamable>0</streamable>
<ontour>0</ontour>
<stats><listeners>22978</listeners>
<playcount>737309</playcount>
</stats>
<similar></similar>
<tags><tag><name>rock</name>
<url>https://www.last.fm/tag/rock</url>
</tag>
<tag><name>classic rock</name>
<url>https://www.last.fm/tag/classic+rock</url>
</tag>
<tag><name>80s</name>
<url>https://www.last.fm/tag/80s</url>
</tag>
<tag><name>folk rock</name>
<url>https://www.last.fm/tag/folk+rock</url>
</tag>
<tag><name>heartland rock</name>
<url>https://www.last.fm/tag/heartland+rock</url>
</tag>
</tags>
<bio><links><link rel="original" href="https://last.fm/music/+noredirect/Tom+Petty+&amp;+The+Heartbreakers/+wiki"></link>
</links>
<published>20 Feb 2009, 01:38</published>
<summary>Tom Petty and the Heartbreakers is an American rock band, formed in 1976 by Tom Petty, Mike Campbell, and Benmont Tench and known for hit singles such as &quot;American Girl&quot;, &quot;Breakdown&quot; and &quot;Mary Jane&apos;s Last Dance.&quot; &lt;a href=&quot;https://www.last.fm/music/+noredirect/Tom+Petty+&amp;+The+Heartbreakers&quot;&gt;Read more on Last.fm&lt;/a&gt;</summary>
<content>Tom Petty and the Heartbreakers is an American rock band, formed in 1976 by Tom Petty, Mike Campbell, and Benmont Tench and known for hit singles such as &quot;American Girl&quot;, &quot;Breakdown&quot; and &quot;Mary Jane&apos;s Last Dance.&quot; &lt;a href=&quot;https://www.last.fm/music/+noredirect/Tom+Petty+&amp;+The+Heartbreakers&quot;&gt;Read more on Last.fm&lt;/a&gt;. User-contributed text is available under the Creative Commons By-SA License; additional terms may apply.</content>
</bio>
</artist>
</lfm>
